pandas_data_cleaner/__init__.py
pandas_data_cleaner/base.py
pandas_data_cleaner/exceptions.py
pandas_data_cleaner/strategies.py
tests/utils/__init__.py
tests/utils/models.py
tests/utils/strategies.py
pandas_data_cleaner-0.0.1.dist-info/LICENSE
pandas_data_cleaner-0.0.1.dist-info/METADATA
pandas_data_cleaner-0.0.1.dist-info/WHEEL
pandas_data_cleaner-0.0.1.dist-info/top_level.txt
pandas_data_cleaner-0.0.1.dist-info/RECORD
