Metadata-Version: 2.1
Name: pandas-data-cleaner
Version: 0.0.1
Summary: A package for aid with data cleaning using pandas.
Home-page: https://github.com/Salaah01/pd-data-cleaner
Author: Salaah Amin
License: MIT
Platform: UNKNOWN
Classifier: Intended Audience :: Developers
Classifier: Operating System :: OS Independent
Classifier: Programming Language :: Python
Classifier: Programming Language :: Python :: 3
Classifier: Programming Language :: Python :: 3 :: Only
Classifier: Programming Language :: Python :: 3.6
Classifier: Programming Language :: Python :: 3.7
Classifier: Programming Language :: Python :: 3.8
Classifier: Programming Language :: Python :: 3.9
Classifier: Programming Language :: Python :: 3.10
Classifier: Topic :: Software Development :: Libraries :: Python Modules
Requires-Python: >=3.6.1
Requires-Dist: pandas (>=1.0.0)
